MANIFEST.in
README
pypi-overview.rst
setup.cfg
setup.py
circuits_minpor/__init__.py
circuits_minpor/date_format.js
circuits_minpor/functions.js
circuits_minpor/portal.py
circuits_minpor/portlet.py
circuits_minpor/utils.py
circuits_minpor.egg-info/PKG-INFO
circuits_minpor.egg-info/SOURCES.txt
circuits_minpor.egg-info/dependency_links.txt
circuits_minpor.egg-info/requires.txt
circuits_minpor.egg-info/top_level.txt
circuits_minpor/portlets/__init__.py
circuits_minpor/portlets/display.py
circuits_minpor/portlets/helloworld.py
circuits_minpor/portlets/servertime.py
circuits_minpor/portlets/templates/helloworld-l10n_de.properties
circuits_minpor/portlets/templates/helloworld.pyhtml
circuits_minpor/portlets/templates/servertime-l10n.properties
circuits_minpor/portlets/templates/servertime-l10n_de.properties
circuits_minpor/portlets/templates/servertime.pyhtml
circuits_minpor/portlets/templates/themes/default/globe.ico
circuits_minpor/templates/_dashboard.pyhtml
circuits_minpor/templates/_portlet.pyhtml
circuits_minpor/templates/_portlet_edited.pyhtml
circuits_minpor/templates/_solo.pyhtml
circuits_minpor/templates/l10n.properties
circuits_minpor/templates/l10n_de.properties
circuits_minpor/templates/l10n_en.properties
circuits_minpor/templates/l10n_fr.properties
circuits_minpor/templates/portal.pyhtml
circuits_minpor/templates/themes/default/close-tab-active.png
circuits_minpor/templates/themes/default/close-tab.png
circuits_minpor/templates/themes/default/edit-solo.png
circuits_minpor/templates/themes/default/edit.png
circuits_minpor/templates/themes/default/favicon.ico
circuits_minpor/templates/themes/default/finish-editing.png
circuits_minpor/templates/themes/default/fullscreen.png
circuits_minpor/templates/themes/default/mipypo.css
circuits_minpor/templates/themes/default/title-bg-hover.png
circuits_minpor/templates/themes/default/title-bg.png
tests/TestPortal.py
tests/__init__.py