Metadata-Version: 1.0
Name: circuits-minpor
Version: 0.3
Summary: A minimal portal based on the circuits component library.
Home-page: http://packages.python.org/circuits-minpor
Author: Michael N. Lipp
Author-email: mnl@mnl.de
License: GPL
Keywords: circuits portal
Platform: UNKNOWN
Classifier: Development Status :: 3 - Alpha
Classifier: License :: OSI Approved :: GNU General Public License (GPL)
